ahd/__init__.py
ahd/__main__.py
ahd/autocomplete.py
ahd/cli.py
ahd/configuration.py
ahd-1.0.0.dist-info/LICENSE
ahd-1.0.0.dist-info/METADATA
ahd-1.0.0.dist-info/WHEEL
ahd-1.0.0.dist-info/entry_points.txt
ahd-1.0.0.dist-info/top_level.txt
ahd-1.0.0.dist-info/RECORD
