Metadata-Version: 2.1
Name: ahd
Version: 1.0.0
Summary: Create ad-hoc macros to be dispatched in their own namespace.
Author: Kieran Wood
Author-email: kieran@canadiancoding.ca
Project-URL: User Docs, https://ahd.readthedocs.io/en/latest/
Project-URL: API Docs, https://kieranwood.ca/ahd
Project-URL: Source, https://github.com/Descent098/ahd
Project-URL: Bug Report, https://github.com/Descent098/ahd/issues/new?assignees=Descent098&labels=bug&template=bug_report.md&title=%5BBUG%5D
Project-URL: Feature Request, https://github.com/Descent098/ahd/issues/new?assignees=Descent098&labels=enhancement&template=feature_request.md&title=%5BFeature%5D
Project-URL: Roadmap, https://github.com/Descent098/ahd/projects
Classifier: Programming Language :: Python :: 3
Classifier: Operating System :: OS Independent
Classifier: Development Status :: 4 - Beta
License-File: LICENSE
Requires-Dist: docopt
Requires-Dist: colored
Requires-Dist: pyyaml
Requires-Dist: fuzzywuzzy
Requires-Dist: python-Levenshtein
Requires-Dist: mkdocs
Requires-Dist: pdoc3
Provides-Extra: dev
Requires-Dist: nox ; extra == 'dev'
Requires-Dist: pytest ; extra == 'dev'
